whitepaper/__init__.py
whitepaper/version.py
whitepaper-0.0.0.dist-info/METADATA
whitepaper-0.0.0.dist-info/WHEEL
whitepaper-0.0.0.dist-info/top_level.txt
whitepaper-0.0.0.dist-info/zip-safe
whitepaper-0.0.0.dist-info/RECORD
