Metadata-Version: 2.1
Name: whitepaper
Version: 0.0.0
Summary: A package for report generation
Home-page: https://www.lockhartlab.org
Author: C. Lockhart
Author-email: chris@lockhartlab.org
License: UNKNOWN
Platform: UNKNOWN
